abyssal_pytorch/__init__.py
abyssal_pytorch/abyssal_pytorch.py
abyssal_pytorch/data.py
abyssal_pytorch/train.py
abyssal_pytorch-0.0.5.dist-info/METADATA
abyssal_pytorch-0.0.5.dist-info/WHEEL
abyssal_pytorch-0.0.5.dist-info/top_level.txt
abyssal_pytorch-0.0.5.dist-info/RECORD
